ssm/__init__.py
ssm/__main__.py
ssm/_version.py
ssm/abcs/__init__.py
ssm/abcs/loggable.py
ssm/api/__init__.py
ssm/api/environment.py
ssm/api/manager.py
ssm/bin/__init__.py
ssm/bin/ssm.py
ssm/cli/__init__.py
ssm/cli/args.py
ssm/cli/options.py
ssm/cli/wrapper.py
ssm/util/__init__.py
aws_ssm_tool-2024.3.14.5.51.dist-info/METADATA
aws_ssm_tool-2024.3.14.5.51.dist-info/WHEEL
aws_ssm_tool-2024.3.14.5.51.dist-info/entry_points.txt
aws_ssm_tool-2024.3.14.5.51.dist-info/top_level.txt
aws_ssm_tool-2024.3.14.5.51.dist-info/RECORD
